{
  "cities": [
    {
      "city": "Vienna",
      "lat": 48.2083,
      "lng": 16.3725
    },
    {
      "city": "Villach",
      "lat": 46.6167,
      "lng": 13.8333
    },
    {
      "city": "Vernier",
      "lat": 46.2,
      "lng": 6.1
    },
    {
      "city": "Versoix",
      "lat": 46.2833,
      "lng": 6.1667
    },
    {
      "city": "Veyrier",
      "lat": 46.1667,
      "lng": 6.1833
    },
    {
      "city": "Villars-sur-Glâne",
      "lat": 46.7833,
      "lng": 7.1167
    },
    {
      "city": "Volketswil",
      "lat": 47.3906,
      "lng": 8.6953
    },
    {
      "city": "Vacallo",
      "lat": 45.85,
      "lng": 9.0333
    },
    {
      "city": "Vezia",
      "lat": 46.0167,
      "lng": 8.9333
    },
    {
      "city": "Veyras",
      "lat": 46.3,
      "lng": 7.5333
    }
  ]
}
